{
  "EDITOR_STATE": {
    "allProjectFiles": {
      "51d42eb7-acbe-4fe3-a1e9-e6d661026d92": {
        "id": "51d42eb7-acbe-4fe3-a1e9-e6d661026d92",
        "parent": null,
        "name": "new1",
        "type": "DIRECTORY",
        "isDirectory": true,
        "children": [
          "8e40477f-9ca2-4005-913e-122bda6d597c"
        ],
        "isRemovable": false,
        "filePath": "new1"
      },
      "8e40477f-9ca2-4005-913e-122bda6d597c": {
        "id": "8e40477f-9ca2-4005-913e-122bda6d597c",
        "parent": "51d42eb7-acbe-4fe3-a1e9-e6d661026d92",
        "name": "lambda.js",
        "type": "JS_LAMBDA",
        "isDirectory": false,
        "children": [],
        "isRemovable": true,
        "filePath": "new1/lambda.js",
        "code": "exports.handler = function(event, context, callback) {\n    \n    callback(null, {\"message\": \"Successfully executed\"});\n}",
        "config": {
          "runtime": "nodejs8.10",
          "handler": "handler",
          "timeout": 60,
          "memory": 128,
          "layers": []
        },
        "triggers": []
      }
    },
    "deletedFiles": [],
    "rootNode": "51d42eb7-acbe-4fe3-a1e9-e6d661026d92",
    "openFiles": [
      "8e40477f-9ca2-4005-913e-122bda6d597c"
    ],
    "currentFileId": "8e40477f-9ca2-4005-913e-122bda6d597c",
    "resources": {},
    "customTemplate": {
      "dialect": null,
      "definitions": {}
    },
    "envVariables": [
      {
        "lambdaId": "all",
        "varKey": "SIGMA_AWS_ACC_ID",
        "varValue": null,
        "shouldPersist": false,
        "displayOnly": false,
        "editable": false
      }
    ],
    "packageJSON": {
      "dependencies": {}
    }
  },
  "PROJECT_META": {
    "projectName": "new1",
    "projectDescription": "",
    "projectVersion": "1.0.0",
    "projectRegion": "us-east-1",
    "platform": "AWS",
    "platformRegions": {}
  },
  "VCS_STATE": {
    "provider": "GitHub",
    "repo": {
      "name": "new1",
      "url": "https://github.com/sigmavcs/new1"
    }
  }
}